overpayment/__init__.py
overpayment/overpayment.py
overpayment-0.0.2.dist-info/METADATA
overpayment-0.0.2.dist-info/WHEEL
overpayment-0.0.2.dist-info/entry_points.txt
overpayment-0.0.2.dist-info/top_level.txt
overpayment-0.0.2.dist-info/RECORD
