Metadata-Version: 2.1
Name: overpayment
Version: 0.0.2
Summary: Get the Employee Data and Protections Data
Home-page: https://github.com/A284viral/protections_v1
Author: Aviral Srivastava
Author-email: aviralsrivastava284@gmail.com
Classifier: Programming Language :: Python :: 3
Classifier: License :: OSI Approved :: MIT License
Classifier: Operating System :: OS Independent
Requires-Python: >=3.6
Requires-Dist: pandas
Requires-Dist: xlsxwriter
